[
    {
        "input_combination": [
            {
                "type": 1,
                "code": 275,
                "origin_hash": "d2aa4c877edb94a694d14ef605bfd296"
            }
        ],
        "target_uinput": "keyboard",
        "output_symbol": "Control_L",
        "mapping_type": "key_macro"
    },
    {
        "input_combination": [
            {
                "type": 1,
                "code": 276,
                "origin_hash": "d2aa4c877edb94a694d14ef605bfd296"
            }
        ],
        "target_uinput": "keyboard",
        "output_symbol": "Control_L",
        "mapping_type": "key_macro"
    }
]
